ai/__init__.py
ai/starlake/__init__.py
ai/starlake/dagster/__init__.py
ai/starlake/dagster/starlake_dagster_job.py
ai/starlake/dagster/starlake_dagster_orchestration.py
ai/starlake/dagster/aws/__init__.py
ai/starlake/dagster/aws/starlake_dagster_fargate_job.py
ai/starlake/dagster/gcp/__init__.py
ai/starlake/dagster/gcp/starlake_dagster_cloud_run_job.py
ai/starlake/dagster/gcp/starlake_dagster_dataproc_job.py
ai/starlake/dagster/shell/__init__.py
ai/starlake/dagster/shell/starlake_dagster_shell_job.py
starlake_dagster-0.4.3.dist-info/licenses/LICENSE
starlake_dagster-0.4.3.dist-info/METADATA
starlake_dagster-0.4.3.dist-info/WHEEL
starlake_dagster-0.4.3.dist-info/top_level.txt
starlake_dagster-0.4.3.dist-info/RECORD
