Metadata-Version: 2.4
Name: starlake-dagster
Version: 0.4.3
Summary: Starlake Python Distribution For Dagster
Author: Stéphane Manciot
Author-email: stephane.manciot@gmail.com
License: Apache 2.0
License-File: LICENSE
Requires-Dist: starlake-orchestration~=0.4
Provides-Extra: dagster
Provides-Extra: shell
Requires-Dist: dagster-shell; extra == "shell"
Provides-Extra: gcp
Requires-Dist: dagster-gcp; extra == "gcp"
Provides-Extra: aws
Provides-Extra: azure
Dynamic: author
Dynamic: author-email
Dynamic: description
Dynamic: description-content-type
Dynamic: license
Dynamic: license-file
Dynamic: provides-extra
Dynamic: requires-dist
Dynamic: summary
